streaming_stt_nemo/__init__.py
streaming_stt_nemo/configs.py
streaming_stt_nemo-0.3.0.dist-info/LICENSE.md
streaming_stt_nemo-0.3.0.dist-info/METADATA
streaming_stt_nemo-0.3.0.dist-info/WHEEL
streaming_stt_nemo-0.3.0.dist-info/top_level.txt
streaming_stt_nemo-0.3.0.dist-info/RECORD
