Metadata-Version: 2.1
Name: streaming-stt-nemo
Version: 0.3.0
Author: Neongecko
Author-email: developers@neon.ai
License: BSD-3.0
Requires-Python: >3.7.0
License-File: LICENSE.md
Requires-Dist: torch
Requires-Dist: onnxruntime
Requires-Dist: sentencepiece
Requires-Dist: soxr
Requires-Dist: pydub
Requires-Dist: huggingface-hub
